Workbook

Sheet YTD
B2: R9 FAS FY23 TRAVEL
F4: FY22 TRAVEL | U4: FY23 | AJ4: FY22 vs. FY23 | AY4: FY23 TRAVEL TYPE
F5: PLANNED | K5: ACTUALS | P5: UNSPENT | U5: PLANNED | Z5: YTD ACTUALS | AE5: BALANCE
B6: OFFICE OF THE REGIONAL COMMISSIONER (RC)
B7: 9Q - 285X-09-RC20-Q0900000 | F7: 40600 | K7: =sum(K8:O11) -> 0 | P7: =F7-K7 -> 40600 | U7: 93000 | Z7: =sum(Z8:AD11) -> 45600.53 | AE7: =U7-Z7 -> 47399.47
B8: 9Q | F8: 1ST QTR | K8: 0 | U8: 1ST QTR | Z8: ='RC'!BB7 -> 7807.93
B9: 9Q1 | F9: 2ND QTR | K9: 0 | U9: 2ND QTR | Z9: ='RC'!BB8 -> 8141.7
B10: 9Q1B | F10: 3RD QTR | K10: 0 | U10: 3RD QTR | Z10: ='RC'!BB9 -> 18135.55
F11: 4TH QTR | K11: 0 | U11: 4TH QTR | Z11: ='RC'!BB10 -> 11515.35
B15: CUSTOMER & STAKEHOLDER ENGAGEMENT (CASE)
B16: 9QCA - 285X-09-SE20-Q09CA000 | F16: 147763 | K16: =SUM(K17:O20) -> 1842.8 | P16: =F16-K16 -> 145920.2 | U16: 195900 | Z16: =sum(Z17:AD20) -> 131427.21 | AE16: =U16-Z16 -> 64472.79
B17: 9QCAA | F17: 1ST QTR | K17: 16.8 | U17: 1ST QTR | Z17: =CASE!BB7+CASE!BB33+CASE!BB59+CASE!BB83 -> 18826.87
B18: 9QCA1 | F18: 2ND QTR | K18: 41.8 | U18: 2ND QTR | Z18: =CASE!BB8+CASE!BB34+CASE!BB60+CASE!BB84 -> 37762.6
B19: 9QCAA | F19: 3RD QTR | K19: 0 | U19: 3RD QTR | Z19: =CASE!BB9+CASE!BB35+CASE!BB61+CASE!BB85 -> 32645.68
B20: 9QCAB | F20: 4TH QTR | K20: 1784.2 | U20: 4TH QTR | Z20: =CASE!BB10+CASE!BB36+CASE!BB62+CASE!BB86 -> 42192.06
B21: 9QCAE
B24: ASSISTED ACQUISITION SERVICES (AAS)
B25: 9QFA -285X-09-AA20-A09FA00 | K25: =SUM(K26:O29) -> 6669.65 | P25: =F25-K25 -> -6669.65 | U25: 350000 | Z25: =sum(Z26:AD29) -> 73541.28 | AE25: =U25-Z25 -> 276458.72
B26: 9QFA | F26: 1st QTR | K26: 0 | U26: 1ST QTR | Z26: =AAS!BB7+AAS!BB24+AAS!BB39+AAS!BB62 -> 9420.4
B27: 9QFAC | F27: 2nd QTR | K27: 0 | U27: 2ND QTR | Z27: =AAS!BB8+AAS!BB25+AAS!BB40+AAS!BB63 -> 9736.1
B28: 9QFAD | F28: 3rd QTR | K28: 0 | U28: 3RD QTR | Z28: =AAS!BB9+AAS!BB26+AAS!BB41+AAS!BB64 -> 18591.97
B29: 9QFAE | F29: 4th QTR | K29: 6669.65 | U29: 4TH QTR | Z29: =AAS!BB10+AAS!BB27+AAS!BB42+AAS!BB65 -> 35792.81
B33: PERSONAL PROPERTY MANAGEMENT (PPM)
B34: (Sales) | F34: 75500 | K34: =SUM(K35:O38) -> 0 | P34: =F34-K34 -> 75500 | U34: 74300 | Z34: =sum(Z35:AD38) -> 28627.5 | AE34: =U34-Z34 -> 45672.5
B35: Q09SC000-285X-09-GS30-AF200 | F35: 1st QTR | K35: 0 | U35: 1ST QTR | Z35: =PPM!BB7 -> 1126.06
B36: 9QSCB | F36: 2nd QTR | K36: 0 | U36: 2ND QTR | Z36: =PPM!BB8 -> 8089.85
F37: 3rd QTR | K37: 0 | U37: 3RD QTR | Z37: =PPM!BB9 -> 2638.25
F38: 4th QTR | K38: 0 | U38: 4TH QTR | Z38: =PPM!BB10 -> 16773.34
B42: (U&D) | F42: 66000 | K42: =SUM(K43:O46) -> 0 | P42: =F42-K42 -> 66000 | U42: 99700 | Z42: =sum(Z43:AD46) -> 55265.33 | AE42: =U42-Z42 -> 44434.67
B43: K09Y1841-142A-09-GA23-GAF80 | F43: 1st QTR | K43: 0 | U43: 1ST QTR | Z43: =PPM!BB41 -> 2224.29
B44: 9QSCA | F44: 2nd QTR | K44: 0 | U44: 2ND QTR | Z44: =PPM!BB42 -> 15711.36
F45: 3rd QTR | K45: 0 | U45: 3RD QTR | Z45: =PPM!BB43 -> 14371.02
F46: 4th QTR | K46: 0 | U46: 4TH QTR | Z46: =PPM!BB44 -> 22958.66
B50: MISCELLANEOUS (not travel) | F50: FY22 TOTAL COUNT | K50: FY22 TOTAL ACTUALS | P50: FY22 MISC VCH CONCUR FEES | U50: FY23 TOTAL COUNT | Z50: FY23 TOTAL ACTUALS | AE50: FY23 CONCUR FEES
B51: OFFICE OF THE REGIONAL COMMISSIONER (RC) | F51: 2 | K51: 313.6 | P51: 13.6 | U51: 1 | Z51: =SUM('RC'!BB44:BF47) -> 156.8 | AE51: =6.8*U51 -> 6.8
B52: CUSTOMER & STAKEHOLDER ENGAGEMENT (CASE) | F52: 12 | K52: 2185.47 | P52: 81.6 | U52: 16 | Z52: =SUM(CASE!BB104:BF107) -> 2342.11 | AE52: =6.8*U52 -> 108.8
B53: ASSISTED ACQUISITION SERVICES (AAS) | K53: 0 | Z53: =SUM(AAS!BB82:BF85) -> 0
B54: PERSONAL PROPERTY MANAGEMENT (PPM) | K54: 0 | Z54: =SUM(PPM!BB82:BF85) -> 0

Sheet FAS
B2: FY23 ALL FAS Travel
I4: 1ST QUARTER | S4: 2ND QTR | AC4: 3RD QTR | AM4: 4TH QTR | AW4: FAS FY23 TOTAL
I5: ESTIMATE | N5: ACTUALS | S5: ESTIMATE | X5: ACTUALS | AC5: ESTIMATE | AH5: ACTUALS | AM5: ESTIMATE | AR5: ACTUALS | AW5: PLANNED | BB5: ACTUALS | BG5: BALANCE
B6: Traveler | C6: Event Title | D6: Travel Dates | F6: Location | G6: Targeted Audience | H6: Trip Type | AW6: =YTD!U7+YTD!U16+YTD!U25+YTD!U34+YTD!U42 -> 812900 | BB6: =SUM(YTD!Z7+YTD!Z16+YTD!Z25+YTD!Z34+YTD!Z42) -> 334461.85 | BG6: =AW6-BB6 -> 478438.15
B7: Stacey Franklin | C7: CASE Leadership Meet | D7: 44815 | E7: 44819 | F7: Boston, MA | G7: Leadership | H7: D03 | I7: 2038.84 | N7: 1788.63 | AW7: 1ST QTR | BB7: =SUM(N7:R264) -> 33395.11
B8: Christina Bowman | C8: Conference | D8: 44846 | E8: 44848 | F8: San Jose, CA | G8: Conference | H8: D07 | I8: 880.08 | N8: 908.59 | AW8: 2ND QTR | BB8: =SUM(X7:AB263) -> 79194.71
B9: Jacqueline Sullo | C9: AAS Directors Meeting | D9: 44851 | E9: 44854 | F9: Denver, CO | G9: Leadership | H9: D02 | I9: 1333.38 | N9: 1288.08 | AW9: 3RD QTR | BB9: =SUM(AH7:AL263) -> 85074.87
B10: Joel Fada | C10: AAS Directors Meeting | D10: 44851 | E10: 44855 | F10: Denver, CO | G10: Leadership | H10: D03 | I10: 1734.37 | N10: 1782.83 | AW10: 4TH QTR | BB10: =sum(AR7:AV264) -> 130044.12
B11: Daniel Thiel | C11: BCS Technical Eval | D11: 44858 | E11: 44860 | F11: Bonita, CA | G11: Customer | H11: D02 | I11: 1053.63 | N11: 1026.56 | BB11: =SUM(BB7:BF10) -> 327708.81
B12: Mark Reiss | C12: Local Travel Toll/Customer Visits | D12: 44853 | E12: 44867 | F12: Various | G12: Customer | H12: D04 | I12: - | N12: 31.8
B13: Diana Lynch-Maldonado | C13: BCS Technical Eval | D13: 44858 | E13: 44862 | F13: Bonita, CA | G13: Customer | H13: D02 | I13: 1396.38 | N13: 1358.46
B14: Daniel Thiel | C14: FAS R9 Leadership Meet | D14: 44872 | E14: 44875 | F14: San Diego, CA | G14: Leadership | H14: D03 | I14: 1324.22 | N14: 1263.15
B15: Christopher Slavens | C15: FAS R9 Leadership Offsite Meeting | D15: 44872 | E15: 44875 | F15: San Diego, CA | G15: Leadership | H15: D03 | I15: 1509.67 | N15: 1282.05
B16: Stacey Franklin | C16: FAS R9 Leadership Offsite Meeting | D16: 44872 | E16: 44875 | F16: San Diego, CA | G16: Leadership | H16: D03 | I16: 1559.67 | N16: 1152.1
B17: Drew Della Valle | C17: FAS R9 Leadership Offsite Meeting | D17: 44872 | E17: 44875 | F17: San Diego, CA | G17: Leadership | H17: D03 | I17: 1057.65 | N17: 1138.4
B18: Sandra Klar | C18: FAS R9 Leadership Offsite Meeting | D18: 44872 | E18: 44875 | F18: San Diego, CA | G18: Leadership | H18: D03 | I18: 1104.87 | N18: 1085.89
B19: Sindi Cheng-Nishimura | C19: FAS R9 Leadership Offsite Meeting | D19: 44872 | E19: 44875 | F19: San Diego, CA | G19: Leadership | H19: D03 | I19: 1076.33 | N19: 1126.06
B20: Charles Lee | C20: FAS R9 Leadership Meeting | D20: 44872 | E20: 44875 | F20: San Diego, CA | G20: Leadership | H20: D03 | I20: 995.12 | N20: 893.93
B21: Elizabeth Belenis | C21: FAS R9 Leadership Meeting | D21: 44872 | E21: 44875 | F21: San Diego, CA | G21: Leadership | H21: D03 | I21: 1091.87 | N21: 1074.75
B22: Jacqueline Sullo | C22: FAS R9 Leadership Offsite Meeting | D22: 44872 | E22: 44875 | F22: San Diego, CA | G22: Leadership | H22: D03 | I22: 1063.57 | N22: 1023.96
B23: Joel Fada | C23: FAS R9 Leadership Offsite Meeting | D23: 44872 | E23: 44875 | F23: San Diego, CA | G23: Leadership | H23: D03 | I23: 1532.45 | N23: 1467.47
B24: Nathan Dolezal | C24: FAS R9 Leadership Offsite Meeting | D24: 44872 | E24: 44875 | F24: San Diego, CA | G24: Leadership | H24: D03 | I24: 1291.87 | N24: 1481.54
B25: Ryan Hagan | C25: Natural Disaster Conference | D25: 44873 | E25: 44875 | F25: Anaheim, CA | G25: Customer | H25: D02 | I25: 645.12 | N25: 607.5
B26: Christina Bowman | C26: Downtown SD TEB | D26: 44858 | E26: 44862 | F26: San Diego, CA | G26: Customer | H26: D04 | I26: - | N26: 131.8
B27: Clint Steele | C27: Natural Disaster Conference _Parking | D27: 44874 | E27: 44880 | F27: Anaheim, CA | G27: Customer | H27: D04 | I27: - | N27: 46.8
B28: Andrew Nguyen | C28: GOV Parking _ SID conference | D28: 44884 | E28: 44885 | F28: Los Angeles, CA | G28: Customer | H28: D04 | I28: - | N28: 39.8
B29: William Villarroel | C29: FAS R9 Leadership Offsite Meeting | D29: 44872 | E29: 44875 | F29: San Diego, CA | G29: Leadership | H29: D03 | I29: 1116.88 | N29: 1109.87
B30: Michelle Stansberry | C30: Customer Visit | D30: 44886 | E30: 44887 | F30: Las Vegas, NV | G30: Customer | H30: D02 | I30: 268.62 | N30: 235.62
B31: Michelle Stansberry | C31: Customer Visit | D31: 44886 | E31: 44895 | F31: Las Vegas, NV | G31: Customer | H31: D02 | I31: 1016.37 | N31: 1114.43
B32: Maria Rodriguez | C32: Customer Visits & Training Herlong NV | D32: 44886 | E32: 44887 | F32: Reno, NV | G32: Customer | H32: D02 | I32: 1172.4 | N32: 1091.86
B33: Florence Francis | C33: CANCELED: Customer Visits | D33: 44880 | E33: 44882 | F33: Barstow, CA | G33: Customer | H33: D02 | I33: 738.95 | N33: -
B34: Casey Kelley | C34: FAS Leadership Council Meet | D34: 44900 | E34: 44904 | F34: Washington, DC | G34: Leadership | H34: D02 | I34: 2046.95 | N34: 2230.27
B35: Stacey Franklin | C35: CASE Leadership Meet | D35: 44906 | E35: 44910 | F35: Kansas City, MO | G35: Leadership | H35: D03 | I35: 1926.67 | N35: 1837.97
B36: Michele Tobin | C36: BD Offsite Meeting | D36: 44900 | E36: 44903 | F36: San Francisco, CA | G36: Staff | H36: D03 | I36: 1892.81 | N36: 1659.04
B37: William Villarroel | C37: FAS R9 COS Interviews | D37: 44916 | E37: 44917 | F37: San Diego, CA | G37: Internal Mtng | H37: D01 | I37: 594.87 | N37: 573.15
B38: Kerry Durkan | C38: BD Team Meet | D38: 44901 | E38: 44903 | F38: San Francisco, CA | G38: Staff | H38: D04 | I38: - | N38: 133.5
B39: Katina Watson | C39: BD Team Meet | D39: 44901 | E39: 44903 | F39: San Francisco, CA | G39: Staff | H39: D04 | I39: - | N39: 120.43
B40: Michele Tobin | C40: FAS R9 Leadership Offsite Meeting | D40: 44872 | E40: 44875 | F40: San Diego, CA | G40: Leadership | H40: D03 | I40: 1364.96 | N40: 1288.82
B41: Stacey Franklin | C41: CASE Leadership Offsite | D41: 44948 | E41: 44953 | F41: Denver, CO | G41: Leadership | H41: D03 | S41: 2402.53 | X41: 2423.67
B42: Jacqueline Sullo | C42: AAS Core Realignment Meeting | D42: 44943 | E42: 44946 | F42: Atlanta, GA | G42: Internal Mtng | H42: D03 | S42: 1359.13 | X42: 1559.09
B43: Stephon Jackson | C43: FCN 416 Conference (Presenter) | D43: 44949 | E43: 44953 | F43: San Diego, CA | G43: Customers | H43: D02 | S43: 2018.46 | X43: 1885.06
B44: Cynthis McKeague | C44: Customer Visits | D44: 44962 | E44: 44967 | F44: IWAkuni, JPN | G44: Customer | H44: D02 | S44: 2199.42 | X44: 2000.42
B45: Joseph Adams | C45: FCN 416 Conference (Presenter) | D45: 44948 | E45: 44953 | F45: San Diego, CA | G45: Customers | H45: D02 | S45: 2206.76 | X45: 1739.47
B46: Sid Frazier | C46: Customer Visits | D46: 2/5/23 | E46: 44965 | F46: IWAkuni, JPN | G46: Customer | H46: D02 | S46: 1019.27 | X46: 1036.8
B47: Nathan Dolezal | C47: Alliant 2 PMR/AFCEA 2023 | D47: 44969 | E47: 44974 | F47: San Diego, CA | G47: Customer | H47: D02 | S47: 2028.32 | X47: 1707.94
B48: Sharon Gorospe | C48: FCN416 Conference (Presenter) | D48: 44948 | E48: 44953 | F48: San Diego, CA | G48: Customers | H48: D02 | S48: 1350.47 | X48: 1150.47
B49: Charles Lee | C49: AFCEA WEST 2023 | D49: 44969 | E49: 44974 | F49: San Diego, CA | G49: Customer | H49: D02 | S49: 1768.74 | X49: 1752.67
B50: Clint Steele | C50: AFCEA WEST 2023 | D50: 44971 | E50: 44973 | F50: San Diego, CA | G50: Customer | H50: D02 | S50: 728.12 | X50: 662.12
B51: Brandy Untalan | C51: FY23 Shadowing Prog | D51: 44966 | E51: 44975 | F51: San Diego, CA | G51: Leadership | H51: D01 | S51: 6624.36 | X51: 6590.66
B52: Andrew Nguyen | C52: Customer Visits | D52: 44978 | E52: 44979 | F52: Ridgecrest, CA | G52: Customer | H52: D02 | S52: 250.43 | X52: 250.43
B53: Steven Collins | C53: FCN416 Conference (Presenter) | D53: 44949 | E53: 44953 | F53: San Diego, CA | G53: Customers | H53: D04 | S53: - | X53: 42
B54: Elizabeth Belenis | C54: VA & Executive Level Visits | D54: 44956 | E54: 44959 | F54: Santa Clara, CA | G54: Leadership | H54: D02 | S54: 1179.74 | X54: 1401.89
B55: Ronald Eisley | C55: Asia Pacific Senior Visit Prep | D55: 44979 | E55: 44982 | F55: Seoul, KOR | G55: Leadership | H55: D03 | S55: 1199.5 | X55: 1352.66
B56: Stacey Franklin | C56: Asia Pacific Senior Visit Prep | D56: 44975 | E56: 44982 | F56: Tokyo, JPN/ Seoul, KOR | G56: Foreign | H56: D40 | S56: 2915.02 | X56: 2873.77
B57: Christopher Slavens | C57: Asia Pacific Senior Visit Prep | D57: 44975 | E57: 44982 | F57: Tokyo, JPN/Seoul, KOR | G57: Foreign | H57: D40 | S57: 3372.02 | X57: 3279
B58: Clevester Hines | C58: AAS TDL Summit Training | D58: 44978 | E58: 44981 | F58: Jacksonville, FL | G58: Customer | H58: D02 | S58: 1137.07 | X58: 1144.59
B59: Casey Kelley | C59: Leadership Council Meet | D59: 44978 | E59: 44981 | F59: Philadelphia, PA | G59: Leadership | H59: D03 | S59: 1433.68 | X59: 1640.99
B60: Sharon Gorospe | C60: SASP Review | D60: 44983 | E60: 44988 | F60: Phoenix, AZ | G60: Customers | H60: D02 | S60: 2136.22 | X60: 2397.48
B61: Stephon Jackson | C61: SASP Review | D61: 44983 | E61: 44988 | F61: Phoenix, AZ | G61: Customers | H61: D02 | S61: 1863.97 | X61: 2098.87
B62: Steven Collins | C62: SASP Review | D62: 44983 | E62: 44988 | F62: Phoenix, AZ | G62: Customers | H62: D02 | S62: 2013.96 | X62: 2174.52
B63: Sing Cheng | C63: HAI Heli Expo 2023 | D63: 44991 | E63: 44995 | F63: Atlanta, GA | G63: Customer | H63: D02 | S63: 1434.4 | X63: 1336.25
B64: Stephon Jackson | C64: Air Force Strike Board Meeting | D64: 44993 | E64: 44994 | F64: Tucson, AZ | G64: Customers | H64: D02 | S64: 625.57 | X64: 645.24
B65: Helen Thach | C65: Air Force Strike Board | D65: 44993 | E65: 44994 | F65: Tucson, AZ | G65: Customer | H65: D02 | S65: 1204.67 | X65: 1132.9
... B68: Sindi Cheng-Nishimura | C68: Air Force Strike Board | D68: 44993 | E68: 44994 | F68: Tucson, AZ | G68: Customer | H68: D02 | S68: 802.11 | X68: 768.56
B69: Christina Bowman | C69: AFCEA West 2023 Conve | D69: 44980 | E69: 44980 | F69: San Diego, CA | G69: Customer | H69: D04 | S69: - | X69: 38.84
B70: Christina Bowman | C70: Alliant 2 PMR | D70: 44970 | E70: 44970 | F70: San Diego, CA | G70: Customer | H70: D04 | S70: - | X70: 38.84
B71: Joy Wahlmann | C71: Alliant 2 PMR/AFCEA 2023 | D71: 44970 | E71: 44970 | F71: San Diego, CA | G71: Customer | H71: D04 | S71: - | X71: 53.48
B72: Nader Mobasseri | C72: SSC Leadership Meeting | D72: 44970 | E72: 44970 | F72: San Diego, CA | G72: Customer | H72: D04 | S72: - | X72: 84.1
B73: Sharon Gorospe | C73: Nevada State Agency Review of Operations | D73: 45005 | E73: 45009 | F73: Reno, NV | G73: CANCELLED | H73: D02 | S73: 1128.1 | X73: -
B74: Diana Lynch-Maldonado | C74: SSC Leadership Meeting | D74: 44992 | E74: 44995 | F74: Los Angeles, CA | G74: Customer | H74: D02 | S74: 978.78 | X74: 1035.25
B75: Nonya Montano | C75: SSC IA Review Meet | D75: 44992 | E75: 44995 | F75: Los Angeles, CA | G75: Customer | H75: D02 | S75: 1003.46 | X75: 1072.9
B76: Nonya Montano | C76: SSC IA Review Meet | D76: 44992 | E76: 44995 | F76: Los Angeles, CA | G76: Customer | H76: D02 | S76: 1003.46 | X76: 1072.9
B77: Clevester Hines | C77: SSC IA Review Meet | D77: 44992 | E77: 44995 | F77: Los Angeles, CA | G77: Customer | H77: D02 | S77: 1652.46 | X77: 1466.71
B78: Daniel Thiel | C78: SSC IA Review Meet | D78: 44992 | E78: 44995 | F78: Los Angeles, CA | G78: Customer | H78: D02 | S78: 1274.91 | X78: 1158.19
B79: Karina Pohlmann | C79: SSC Leadership Meeting | D79: 44992 | E79: 44995 | F79: Los Angeles, CA | G79: Customer | H79: D02 | S79: 1296.61 | X79: 1297.53
B80: Pamela Ervin | C80: Customer Visit | D80: 44979 | E80: 44980 | F80: Pleasanton, CA | G80: Customer | H80: D02 | S80: 448.47 | X80: 637.73
B81: Zach Dean | C81: Heli-Expo | D81: 44991 | E81: 44993 | F81: Atlanta, GA | G81: Customer | H81: D02 | S81: 1233.95 | X81: 1264.97
B82: Sing Cheng | C82: HAI Heli Expo 2023 | D82: 44991 | E82: 44995 | F82: Atlanta, GA | G82: Customer | H82: D02 | S82: 1434.4 | X82: 1336.25
B83: Sharon Gorospe | C83: NV Surplus Property Review of Operations | D83: 45005 | E83: 45008 | F83: Reno, NV | G83: Customers | H83: D02 | S83: 1215.05 | X83: 1356.32
B84: Stephon Jackson | C84: NV Surplus Property Review of Operations | D84: 45005 | E84: 45009 | F84: Reno, NV | G84: Customers | H84: D02 | S84: 1500.32 | X84: 1435.13
B85: Casey Kelley | C85: QTRLY F4 Meeting | D85: 44998 | E85: 45001 | F85: Atlanta, GA | G85: Leadership | H85: D02 | S85: 1451.39 | X85: 1559.73
... B89: Casey Kelley | C89: CASE Leadership/Staff Meet | D89: 45005 | E89: 45008 | F89: San Francisco, CA | G89: Leadership | H89: D03 | S89: 1629.9 | X89: 1760.93
B90: Cynthia McKeague | C90: NAM Meeting with Leadership | D90: 45010 | E90: 45016 | F90: DC, WA | G90: Leadership | H90: D03 | S90: - | X90: -
B91: Cynthia McKeague | C91: RES 2023 Conference | D91: 45016 | E91: 45026 | F91: Las Vegas NV | G91: Conference | H91: D05 | S91: 3858.09 | X91: 3216.77
B92: Christopher Slavens | C92: R9 CASE Leadership Meet | D92: 45005 | E92: 45008 | F92: San Francisco, CA | G92: Leadership | H92: D03 | S92: 2683.4 | X92: 2610.32
B93: Stacey Franklin | C93: R9 CASE Leadership Meet | D93: 45004 | E93: 45009 | F93: San Francisco, CA | G93: Leadership | H93: D03 | S93: 3286.17 | X93: 3130.33
B94: Elizabeth Belenis | C94: CANCELLED: R9 CASE Leadership Meet | D94: 45005 | E94: 45009 | F94: San Francisco, CA | G94: Leadership | H94: D03 | S94: 2115.62 | X94: -
B95: Kerry Durkan | C95: Leadership Meeting SF Mileage & Parking | D95: 45008 | E95: 45008 | F95: San Francisco, CA | G95: Leadership | H95: D04 | S95: - | X95: 52.38
B96: Joy Wahlmann | C96: Analytics IDIQ Eval Mileage & Parking | D96: 45027 | E96: 45030 | F96: San Diego, CA | G96: Customer | H96: D04 | AC96: - | AH96: 281.58
B97: Nader Mobasseri | C97: Front Line Leaders Conference | D97: 45030 | E97: 45039 | F97: Philadelphia, PA | G97: CANCELLED | H97: D06 | AC97: 1902.96 | AH97: -
B98: Jacqueline Sullo | C98: AAS & Front Line Leader Meet | D98: 45033 | E98: 45037 | F98: Philadelphia, PA | G98: Leadership | H98: D03 | AC98: 1853.62 | AH98: 1961.38
B99: Casey Kelley | C99: Asia Trip | D99: 45026 | E99: 45038 | F99: Japan & Korea | G99: Foreign | H99: D40 | AC99: 8031.74 | AH99: 8229.14
B100: Florence Francis | C100: RES 2023 Conference | D100: 45018 | E100: 45022 | F100: Las Vegas, NV | G100: Customers | H100: D05 | AC100: 1494.17 | AH100: 1199.32
B101: Michele Tobin | C101: CASE Off Site Business Meet | D101: 45033 | E101: 45038 | F101: Annapolis, MD | G101: Leadership | H101: D03 | AC101: 1214.68 | AH101: 1288.45
B102: Charles Lee | C102: CASE Off Site Business Meet | D102: 45033 | E102: 45036 | F102: Annapolis, MD | G102: Leadership | H102: D03 | AC102: 1445.68 | AH102: 1262.48
B103: Stacey Franklin | C103: CASE Off Site Business Meet | D103: 45032 | E103: 45036 | F103: Annapolis, MD | G103: Leadership | H103: D03 | AC103: 2284.27 | AH103: 2175.83
B104: Clint Steele | C104: Warriors West 2023/Customer Visits | D104: 45020 | E104: 45022 | F104: San Diego, CA | G104: Customer | H104: D02 | AC104: 700.12 | AH104: 671.42
B105: Alberto Gomez | C105: Tech Evaluation Board | D105: 45021 | E105: 45030 | F105: San Diego, CA | G105: Customer | H105: D02 | AC105: 1510.47 | AH105: 1875.08
B106: Steven Collins | C106: ECS Review Training | D106: 45033 | E106: 45037 | F106: Atlanta, GA | G106: Training | H106: D02 | AC106: 1748.47 | AH106: 2008.16
B107: Sidney Frazier | C107: Asia Pacific Senior Visit Prep | D107: 45030 | E107: 45035 | F107: Tokyo, JPN | G107: Leadership | H107: D02 | AC107: 3170 | AH107: 2200.76
...

Sheet RC
B2: FY23 RC Travel
I4: 1ST QUARTER | S4: 2ND QTR | AC4: 3RD QTR | AM4: 4TH QTR | AW4: FY 23 TOTAL
I5: ESTIMATE | N5: ACTUALS | S5: ESTIMATE | X5: ACTUALS | AC5: ESTIMATE | AH5: ACTUALS | AM5: ESTIMATE | AR5: ACTUALS | AW5: PLANNED | BB5: ACTUALS | BG5: BALANCE
B6: 9Q - 285X-09-RC20-Q0900000 | C6: Event Title | D6: Travel Dates | F6: Location | G6: Targeted Audience | H6: Trip Type | AW6: 93000 | BB6: =sum(BB7:BF42) -> 45600.53 | BG6: =AW6-BB6 -> 47399.47
B7: Casey Kelley | C7: Internal Management Meeting | D7: 44830 | E7: 44831 | F7: San Francisco, CA | G7: Internal Mtng | H7: D03 | I7: 628.62 | N7: 838.4 | BB7: =SUM(N7:R42) -> 7807.93 | BG7: 1ST QTR
B8: Jacqueline Sullo | C8: AAS Directors Meeting | D8: 44851 | E8: 44854 | F8: Denver, CO | G8: Leadership | H8: D02 | I8: 1333.38 | N8: 1288.08 | BB8: =SUM(X7:AB42) -> 8141.7 | BG8: 2ND QTR
B9: William Villarroel | C9: FAS R9 Leadership Offsite Meeting | D9: 44872 | E9: 44875 | F9: San Diego, CA | G9: Leadership | H9: D03 | I9: 1116.88 | N9: 1109.87 | BB9: =SUM(AH7:AL42) -> 18135.55 | BG9: 3RD QTR
B10: Jacqueline Sullo | C10: FAS R9 Leadership Offsite Meeting | D10: 44872 | E10: 44875 | F10: San Diego, CA | G10: Leadership | H10: D03 | I10: 1063.57 | N10: 1023.96 | BB10: =SUM(AR7:AV42) -> 11515.35 | BG10: 4TH QTR
B11: Casey Kelley | C11: FAS Leadership Council Meet | D11: 44900 | E11: 44904 | F11: Washington, DC | G11: Leadership | H11: D02 | I11: 2046.95 | N11: 2230.27
B12: Casey Kelley | C12: FAS R9 COS Interviews | D12: 44914 | E12: 44915 | F12: San Francisco, CA | G12: Internal Mtng | H12: D02 | I12: 604.37 | N12: 744.2
B13: William Villarroel | C13: FAS R9 COS Interviews | D13: 44916 | E13: 44917 | F13: San Diego, CA | G13: Internal Mtng | H13: D01 | I13: 594.87 | N13: 573.15
B14: Jacqueline Sullo | C14: AAS Core Realignment Meeting | D14: 44943 | E14: 44946 | F14: Atlanta, GA | G14: Internal Mtng | H14: D03 | S14: 1359.13 | X14: 1559.09
B15: Casey Kelley | C15: Leadership Council Meet | D15: 44978 | E15: 44981 | F15: Philadelphia, PA | G15: Leadership | H15: D03 | S15: 1433.68 | X15: 1640.99
B16: Casey Kelley | C16: QTRLY F4 Meeting | D16: 44998 | E16: 45001 | F16: Atlanta, GA | G16: Leadership | H16: D02 | S16: 1451.39 | X16: 1559.73
B17: Casey Kelley | C17: CASE Leadership/Staff Meet | D17: 45005 | E17: 45008 | F17: San Francisco, CA | G17: Leadership | H17: D03 | S17: 1629.9 | X17: 1760.93
B18: Christina Bowman | C18: CASE Leadership/Staff Meet | D18: 45005 | E18: 45008 | F18: San Francisco, CA | G18: Leadership | H18: D03 | S18: 1665.98 | X18: 1620.96
B19: Jacqueline Sullo | C19: AAS & Front Line Leader Meet | D19: 45033 | E19: 45037 | F19: Philadelphia, PA | G19: Leadership | H19: D03 | AC19: 1853.62 | AH19: 1961.38
B20: Casey Kelley | C20: Asia Trip | D20: 45026 | E20: 45038 | F20: Japan & Korea | G20: Foreign | H20: D40 | AC20: 8031.74 | AH20: 8229.14
B21: Jacqueline Sullo | C21: FAS R9 Leadership Offsite Meeting | D21: 45047 | E21: 45050 | F21: Phoenix, AZ | G21: Leadership | H21: D03 | AC21: 1057.67 | AH21: 1094.75
B22: Christina Bowman | C22: FAS R9 Leadership Offsite Meeting | D22: 45047 | E22: 45050 | F22: Phoenix, AZ | G22: Leadership | H22: D03 | AC22: 1114.39 | AH22: 1111.06
B23: William Villarroel | C23: FAS R9 Leadership Offsite Meeting | D23: 45047 | E23: 45050 | F23: Phoenix, AZ | G23: Leadership | H23: D03 | AC23: 1245.38 | AH23: 1092.65
B24: Casey Kelley | C24: FAS R9 Leadership Offsite Meeting | D24: 45047 | E24: 45051 | F24: Phoenix, AZ | G24: Leadership | H24: D03 | AC24: 1194.39 | AH24: 1109.87
B25: Casey Kelley | C25: CANCELLED: (See below) Leadership Council Meet | D25: 45089 | E25: 45093 | F25: Washington, DC | G25: Leadership | H25: D03 | AC25: 2279.61 | AH25: -
B26: Casey Kelley | C26: Leadership Council Meet | D26: 45089 | E26: 45096 | F26: Washington, DC | G26: Leadership | H26: D03 | AC26: 3349.4 | AH26: 3075.17
B27: Christina Bowman | C27: SWRMC at Naval Base Mileage | D27: 45056 | E27: 45056 | F27: San Diego, CA | G27: Customer | H27: D04 | AC27: - | AH27: 23.83
B28: Casey Kelley | C28: 2023 Government Contract Pricing Summit Mileage & Parking | D28: 45097 | E28: 45099 | F28: San Diego, CA | G28: Customer | H28: D04 | AC28: - | AH28: 260.88
B29: Christina Bowman | C29: 2023 Government Contract Pricing Summit Mileage & Parking | D29: 45097 | E29: 45099 | F29: San Diego, CA | G29: Customer | H29: D04 | AC29: - | AH29: 176.82
B30: Casey Kelley | C30: PPM Divisional Team Bldg Offsite | D30: 45152 | E30: 45154 | F30: Portland, OR | G30: Leadership | H30: D03 | AM30: 1245.25 | AR30: 1324.47
B31: Casey Kelley | C31: Senior Leadership Meeting | D31: 45159 | E31: 45163 | F31: Tacoma, WA | G31: Leadership | H31: D03 | AM31: 1289.27 | AR31: 1225.26
B32: Christina Bowman | C32: AAS, PBS, and CASE NAMs Meeting Mileage & Parking | D32: 45125 | E32: 45125 | F32: San Diego, CA | G32: Leadership | H32: D04 | AM32: - | AR32: 51.83
B33: Christina Bowman | C33: Leadership Offboarding and Transition | D33: 45195 | E33: 45196 | F33: San Francisco, CA | G33: Leadership | H33: D03 | AM33: 729.27 | AR33: 784.24
B34: Casey Kelley | C34: Leadership Offboarding and Transition | D34: 45195 | E34: 45196 | F34: San Francisco, CA | G34: Leadership | H34: D03 | AM34: 739.27 | AR34: 761.12
B35: Casey Kelley | C35: APEX 2 Offsite Events | D35: 45180 | E35: 45184 | F35: Fort Worth TX and Warner Robins GA | G35: Leadership | H35: D03 | AM35: 1402.4 | AR35: 1596.68
B36: Christina Bowman | C36: APEX 2 Offsite Events | D36: 45180 | E36: 45184 | F36: Fort Worth TX and Warner Robins GA | G36: Leadership | H36: D03 | AM36: 1721.29 | AR36: 1838.03
B37: William Villarroel | C37: CASE Leadership Meeting | D37: 45187 | E37: 45191 | F37: Honolulu, HI | G37: Leadership | H37: D03 | AM37: 2607.47 | AR37: 2657.72
B38: Diana Fiesco-Bugarini | C38: APEX 2 Offsite Events | D38: 45180 | E38: 45182 | F38: Forth Worth, TX | G38: Leadership | H38: D03 | AM38: 942.08 | AR38: 1109.44
B39: Casey Kelley | C39: FAS AAS Leadership & NAVWAR Meetings | D39: 45125 | E39: 45127 | F39: San Diego, CA | G39: Leadership | H39: D04 | AM39: - | AR39: 85.4
B40: Diana Fiesco-Bugarini | C40: 50 UNP Office Cleanout Final Walkthrough | D40: 45198 | E40: 45198 | F40: San Francisco, CA | G40: Leadership | H40: D04 | AM40: - | AR40: 81.16
B43: MISCELLANEOUS | C43: Event Title/Desc | D43: Servc/Payment Date | H43: Sub Obj Code
B44: Casey Kelley | C44: Professional Liablity Insurance 2023 | D44: 44916 | F44: N/A | G44: N/A | H44: B04 | I44: - | N44: 156.8 | AW44: MISC | BB44: =SUM(N44:R55) -> 156.8 | BG44: 1ST QTR
BB45: =SUM(X44:AB49) -> 0 | BG45: 2ND QTR
BB46: =SUM(AH44:AL56) -> 0 | BG46: 3RD QTR
BB47: =SUM(AR44:AV56) -> 0 | BG47: 4TH QTR

Sheet CASE
B2: FY23 CASE Travel
I4: 1ST QUARTER | S4: 2ND QTR | AC4: 3RD QTR | AM4: 4TH QTR | AW4: FY23 TOTAL
I5: ESTIMATE | N5: ACTUALS | S5: ESTIMATE | X5: ACTUALS | AC5: ESTIMATE | AH5: ACTUALS | AM5: ESTIMATE | AR5: ACTUALS | AW5: PLANNED | BB5: ACTUALS | BG5: BALANCE
B6: 9QCA & 9QCA1 | C6: Event Title | D6: Travel Dates | F6: Location | G6: Targeted Audience | H6: Trip Type | AW6: 195900 | BB6: =sum(BB7:BF86) -> 131427.21 | BG6: =AW6-BB6 -> 64472.79
B7: Stacey Franklin | C7: CASE Leadership Meet | D7: 44815 | E7: 44819 | F7: Boston, MA | G7: Leadership | H7: D03 | I7: 2038.84 | N7: 1788.63 | AW7: 9QCA | BB7: =SUM(N7:R31) -> 7980.49 | BG7: 1ST QTR
B8: Stacey Franklin | C8: FAS R9 Leadership Offsite Meeting | D8: 44872 | E8: 44875 | F8: San Diego, CA | G8: Leadership | H8: D03 | I8: 1559.67 | N8: 1152.1 | BB8: =SUM(X7:AB31) -> 11165.73 | BG8: 2ND QTR
B9: Michele Tobin | C9: FAS R9 Leadership Offsite Meeting | D9: 44872 | E9: 44875 | F9: San Diego, CA | G9: Leadership | H9: D03 | I9: 1364.96 | N9: 1288.82 | BB9: =SUM(AH7:AL31) -> 6659.72 | BG9: 3RD QTR
B10: Stacey Franklin | C10: CASE Leadership Meet | D10: 44906 | E10: 44910 | F10: Kansas City, MO | G10: Leadership | H10: D03 | I10: 1926.67 | N10: 1837.97 | BB10: =SUM(AR7:AV31) -> 15862.52 | BG10: 4TH QTR
B11: Michele Tobin | C11: BD Offsite Meeting | D11: 44900 | E11: 44903 | F11: San Francisco, CA | G11: Staff | H11: D03 | I11: 1892.81 | N11: 1659.04
B12: Kerry Durkan | C12: BD Team Meet | D12: 44901 | E12: 44903 | F12: San Francisco, CA | G12: Staff | H12: D04 | I12: - | N12: 133.5
B13: Katina Watson | C13: BD Team Meet | D13: 44901 | E13: 44903 | F13: San Francisco, CA | G13: Staff | H13: D04 | I13: - | N13: 120.43
B14: Stacey Franklin | C14: CASE Leadership Offsite | D14: 44948 | E14: 44953 | F14: Denver, CO | G14: Leadership | H14: D03 | S14: 2402.53 | X14: 2423.67
B15: Stacey Franklin | C15: Asia Pacific Senior Visit Prep | D15: 44975 | E15: 44982 | F15: Tokyo, JPN/ Seoul, KOR | G15: Foreign | H15: D40 | S15: 2915.02 | X15: 2873.77
B16: Michele Tobin | C16: Qtrly Leadership Visit | D16: 45005 | E16: 45010 | F16: San Francisco, CA | G16: Leadership | H16: D02 | S16: 2378.96 | X16: 2685.58
B17: Stacey Franklin | C17: R9 CASE Leadership Meet | D17: 45004 | E17: 45009 | F17: San Francisco, CA | G17: Leadership | H17: D03 | S17: 3286.17 | X17: 3130.33
B18: Kerry Durkan | C18: Leadership Meeting SF Mileage & Parking | D18: 45008 | E18: 45008 | F18: San Francisco, CA | G18: Leadership | H18: D04 | S18: - | X18: 52.38
B19: Stacey Franklin | C19: CASE Off Site Business Meet | D19: 45032 | E19: 45036 | F19: Annapolis, MD | G19: Leadership | H19: D03 | AC19: 2284.27 | AH19: 2175.83
B20: Michele Tobin | C20: CASE Off Site Business Meet | D20: 45033 | E20: 45038 | F20: Annapolis, MD | G20: Leadership | H20: D03 | AC20: 1214.68 | AH20: 1288.45
B21: Stacey Franklin | C21: R9 Leadership Offsite Meeting | D21: 45046 | E21: 45051 | F21: Phoenix, AZ | G21: Leadership | H21: D03 | AC21: 1843.11 | AH21: 1843.11
B22: Stacey Franklin | C22: CASE Meeting | D22: 45050 | E22: 45051 | F22: Phoenix, AZ | G22: Leadership | H22: D02 | AC22: 267.22 | AH22: 267.22
B23: Michele Tobin | C23: R9 Leadership Offsite Meeting | D23: 45047 | E23: 45051 | F23: Phoenix, AZ | G23: Leadership | H23: D03 | AC23: 1261.38 | AH23: 1085.11
B24: Michele Tobin | C24: BD Development OffSite Meet | D24: 45138 | E24: 45143 | F24: Oakland, CA | G24: Staff | H24: D03 | AM24: 1700.77 | AR24: 1639
B25: Stacey Franklin | C25: Asia Pacific Senior Visit Prep | D25: 45122 | E25: 45136 | F25: Japan & Korea | G25: Customer | H25: D40 | AM25: 7216.31 | AR25: 7897.78
B26: Michele Tobin | C26: BIG Conference | D26: 45165 | E26: 45172 | F26: Prince George's County MD | G26: Conference | H26: D05 | AM26: 2000.37 | AR26: 1936.08
B27: Stacey Franklin | C27: FAS Commissioner/Leadership Meeting | D27: 45173 | E27: 45176 | F27: Washington, DC | G27: Leadership | H27: D03 | AM27: 1898.07 | AR27: 1818.39
B28: Michele Tobin | C28: Offsite Leadership Meeting | D28: 45187 | E28: 45195 | F28: Honolulu, HI | G28: Leadership | H28: D03 | AM28: 2239.47 | AR28: 2145.19
B29: Katina Watson | C29: BD Team Meeting/San Francisco Office Cleanout | D29: 45139 | E29: 45145 | F29: Oakland/San Francisco, CA | G29: Staff | H29: D04 | AM29: - | AR29: 147.68
B30: Kerry Durkan | C30: BD Team Meeting/San Francisco Office Cleanout | D30: 45139 | E30: 45145 | F30: Oakland/San Francisco, CA | G30: Staff | H30: D04 | AM30: - | AR30: 184.25
B31: Michele Tobin | C31: POV Mileage, Parking, Mileage & Uber | D31: 44972 | E31: 45077 | F31: Los Angeles, CA | G31: N/A | H31: D04 | AM31: - | AR31: 94.15
B32: 9QCAA | C32: Event Title | D32: Travel Dates | F32: Location | G32: Targeted Audience | H32: Trip Type
B33: Sidney Frazier | C33: Customer Visit | D33: 44815 | E33: 44820 | F33: Iwakuni, JPN | G33: Customer | H33: D02 | I33: 1844.79 | N33: 1715.33 | AW33: 9QCAA | BB33: =sum(N33:R57) -> 4963.51 | BG33: 1ST QTR
B34: Brandy Untalan | C34: Customer Visit | D34: 44859 | E34: 44863 | F34: Saipan, MP | G34: Customer | H34: D02 | I34: 1836.21 | N34: 1966.13 | BB34: =SUM(X36:AB57) -> 20086.63 | BG34: 2ND QTR
B35: Christopher Slavens | C35: FAS R9 Leadership Offsite Meeting | D35: 44872 | E35: 44875 | F35: San Diego, CA | G35: Leadership | H35: D03 | I35: 1509.67 | N35: 1282.05 | BB35: =SUM(AH33:AL57) -> 17861.26 | BG35: 3RD QTR
B36: Cynthia McKeague | C36: Customer Visits | D36: 44962 | E36: 44967 | F36: IWAkuni, JPN | G36: Customer | H36: D02 | S36: 2199.42 | X36: 2000.42 | BB36: =SUM(AR33:AV57) -> 16932.88 | BG36: 4TH QTR
B37: Sid Frazier | C37: Customer Visits | D37: 2/5/23 | E37: 44965 | F37: IWAkuni, JPN | G37: Customer | H37: D02 | S37: 1019.27 | X37: 1036.8
B38: Christopher Slavens | C38: Asia Pacific Senior Visit Prep | D38: 44975 | E38: 44982 | F38: Tokyo, JPN/Seoul, KOR | G38: Foreign | H38: D40 | S38: 3372.02 | X38: 3279
B39: Brandy Untalan | C39: FY23 Shadowing Prog | D39: 44966 | E39: 44975 | F39: San Diego, CA | G39: Leadership | H39: D01 | S39: 6624.36 | X39: 6590.66
B40: Ronald Eisley | C40: Asia Pacific Senior Visit Prep | D40: 44979 | E40: 44982 | F40: Seoul, KOR | G40: Leadership | H40: D03 | S40: 1199.5 | X40: 1352.66
B41: Cynthia McKeague | C41: NAM Meeting with Leadership | D41: 45010 | E41: 45016 | F41: DC, WA | G41: Leadership | H41: D03 | S41: - | X41: -
B42: Cynthia McKeague | C42: RES 2023 Conference | D42: 45016 | E42: 45026 | F42: Las Vegas NV | G42: Conference | H42: D05 | S42: 3858.09 | X42: 3216.77
B43: Christopher Slavens | C43: R9 CASE Leadership Meet | D43: 45005 | E43: 45008 | F43: San Francisco, CA | G43: Leadership | H43: D03 | S43: 2683.4 | X43: 2610.32
B44: Christopher Slavens | C44: Asia Trip - Japan & Korea | D44: 45029 | E44: 45038 | F44: JPN & KOR | G44: Foreign | H44: D40 | AC44: 4220.92 | AH44: 5035.79
B45: Ronald Eisley | C45: Asia Trip - Korea | D45: 45035 | E45: 45038 | F45: Seoul, KOR | G45: Leadership | H45: D02 | AC45: 2034.5 | AH45: 1319.5
B46: Christopher Slavens | C46: R9 Leadership Offsite Meeting | D46: 45046 | E46: 45050 | F46: Phoenix, AZ | G46: Leadership | H46: D03 | AC46: 1853.09 | AH46: 1814.57
B47: Sidney Frazier | C47: Asia Pacific Senior Visit Prep | D47: 45030 | E47: 45035 | F47: Tokyo, JPN | G47: Leadership | H47: D02 | AC47: 3170 | AH47: 2200.76
B48: Brandy Untalan | C48: DOI Territorial Climate & Infra Workshop | D48: 45053 | E48: 45058 | F48: Pearl Harbor, HI | G48: Training | H48: D05 | AC48: 5018.49 | AH48: 5047.76
B49: Sidney Frazier | C49: Customer Visits - GSA eTool Training | D49: 45061 | E49: 45065 | F49: Sasebo JPN | G49: Customer | H49: D02 | AC49: 1405.57 | AH49: 1444.41
B50: Ronald Eisley | C50: CANCELLED: Customer Visit | D50: 45101 | E50: 45105 | F50: Seoul, KOR | G50: Customer | H50: D02 | AC50: 1528.25 | AH50: -
B51: Sidney Frazier | C51: Customer Visits | D51: 45082 | E51: 45085 | F51: Misawa AB, JPN | G51: Customer | H51: D02 | AC51: 998.47 | AH51: 998.47
B52: Stacey Franklin | C52: CASE Leadership Offsite | D52: 45144 | E52: 45148 | F52: Fort Worth, TX | G52: Leadership | H52: D03 | AM52: 1909.44 | AR52: 2470.76
B53: Ronald Eisley | C53: Leadership Meeting | D53: 45125 | E53: 45128 | F53: Seoul, KOR | G53: Leadership | H53: D03 | AM53: 1298.25 | AR53: 1367.25
B54: Ronald Eisley | C54: SCM Rep Customer Visit | D54: 45137 | E54: 45142 | F54: Seoul, KOR | G54: Customer | H54: D02 | AM54: 2208.25 | AR54: 2038.26
B55: Sidney Frazier | C55: Leadership Meeting | D55: 45128 | E55: 45136 | F55: Various, JAPAN | G55: Leadership | H55: D02 | AM55: 3540.98 | AR55: 3567.02
B56: Christopher Slavens | C56: Asia Pacific Leadership Meeting | D56: 45122 | E56: 45136 | F56: Various, JAPAN | G56: Leadership | H56: D40 | AM56: 8049.8 | AR56: 7489.59
B57: Christopher Slavens | C57: CANCELLED: FAS Commissoner/Leadership Meeting | D57: 45173 | E57: 45176 | F57: Washington, DC | G57: Leadership | H57: D03 | AM57: 1898.07 | AR57: -
B58: 9QCAB | C58: Event Title | D58: Travel Dates | F58: Location | G58: Targeted Audience | H58: Trip Type
B59: Charles Lee | C59: FAS R9 Leadership Meeting | D59: 44872 | E59: 44875 | F59: San Diego, CA | G59: Leadership | H59: D03 | I59: 995.12 | N59: 893.93 | AW59: 9QCAB | BB59: =SUM(N59:R81) -> 1588.03 | BG59: 1ST QTR
B60: Ryan Hagan | C60: Natural Disaster Conference | D60: 44873 | E60: 44875 | F60: Anaheim, CA | G60: Customer | H60: D02 | I60: 645.12 | N60: 607.5 | BB60: =SUM(X59:AB81) -> 5108.35 | BG60: 2ND QTR
B61: Clint Steele | C61: Natural Disaster Conference _Parking | D61: 44874 | E61: 44880 | F61: Anaheim, CA | G61: Customer | H61: D04 | I61: - | N61: 46.8 | BB61: =SUM(AH59:AL81) -> 5356.34 | BG61: 3RD QTR
B62: Andrew Nguyen | C62: GOV Parking _ SID conference | D62: 44884 | E62: 44885 | F62: Los Angeles, CA | G62: Customer | H62: D04 | I62: - | N62: 39.8 | BB62: =SUM(AR59:AV81) -> 6540.61 | BG62: 4TH QTR
B63: Charles Lee | C63: AFCEA WEST 2023 | D63: 44969 | E63: 44974 | F63: San Diego, CA | G63: Customer | H63: D02 | S63: 1768.74 | X63: 1752.67
B64: Clint Steele | C64: AFCEA WEST 2023 | D64: 44971 | E64: 44973 | F64: San Diego, CA | G64: Customer | H64: D02 | S64: 728.12 | X64: 662.12
B65: Andrew Nguyen | C65: Customer Visits | D65: 44978 | E65: 44979 | F65: Ridgecrest, CA | G65: Customer | H65: D02 | S65: 250.43 | X65: 250.43
B66: Charles Lee | C66: R9 Case Leadership Meet | D66: 45005 | E66: 45009 | F66: San Francisco, CA | G66: Leadership | H66: D03 | S66: 2491.02 | X66: 2443.13
B67: Ryan Hagan | C67: WACE 2023 Conference | D67: 45032 | E67: 45035 | F67: Las Vegas, NV | G67: Conference | H67: D05 | AC67: 1391.97 | AH67: 1356.13
B68: Charles Lee | C68: CASE Off Site Business Meet | D68: 45033 | E68: 45036 | F68: Annapolis, MD | G68: Leadership | H68: D03 | AC68: 1445.68 | AH68: 1262.48
B69: Clint Steele | C69: Warriors West 2023/Customer Visits | D69: 45020 | E69: 45022 | F69: San Diego, CA | G69: Customer | H69: D02 | AC69: 700.12 | AH69: 671.42
B70: Charles Lee | C70: FAS R9 Leadership Meeting | D70: 45047 | E70: 45051 | F70: Phoenix, AZ | G70: Leadership | H70: D03 | AC70: 1448.13 | AH70: 1319.64
B71: Andrew Nguyen | C71: Customer Visits | D71: 45063 | E71: 45064 | F71: Ridgecrest, CA | G71: Customer | H71: D02 | AC71: 250.43 | AH71: 250.43
B72: Waleed Wahbe | C72: NV Apex Accelerator SB Event | D72: 45097 | E72: 45099 | F72: Las Vegas, NV | G72: Customer | H72: D02 | AC72: 516.24 | AH72: 496.24
B73: Ryan Hagan | C73: R4 Leadership Summit | D73: 45124 | E73: 45128 | F73: Orlando, FL | G73: Leadership | H73: D03 | AM73: 1486.28 | AR73: 1953.76
B74: Waleed Wahbe | C74: Customer Visits | D74: 41101 | E74: 45119 | F74: Rancho Mirage, CA | G74: Customer | H74: D02 | AM74: 353.62 | AR74: 308.62
B75: Clint Steele | C75: Navy Gold Coast Customer Meetings | D75: 45133 | E75: 45135 | F75: San Diego, CA | G75: Customer | H75: D02 | AM75: 781.12 | AR75: 641.12
B76: Andrew Nguyen | C76: Customer Visits | D76: 45180 | E76: 45181 | F76: Lompoc, CA | G76: Customer | H76: D02 | AM76: 396.94 | AR76: 375.81
B77: Charles Lee | C77: CASE Leadership Meet | D77: 45187 | E77: 45191 | F77: Honolulu, HI | G77: Leadership | H77: D03 | AM77: 2279.47 | AR77: 2344.14
B78: Waleed Wahbe | C78: Customer Visits | D78: 45180 | E78: 45181 | F78: Lompoc, CA | G78: Customer | H78: D02 | AM78: 376.94 | AR78: 375.81
B79: Waleed Wahbe | C79: Customer Visits | D79: 45175 | E79: 45176 | F79: Ridgecrest, CA | G79: Customer | H79: D02 | AM79: 263.12 | AR79: 243.12
B80: Andrew Nguyen | C80: Customer Visits | D80: 45175 | E80: 45176 | F80: Ridgecrest, CA | G80: Customer | H80: D02 | AM80: 256.12 | AR80: 251.43
B81: Clint Steele | C81: Anaheim Disaster Show | D81: 45196 | E81: 45197 | F81: Anaheim, CA | G81: Customer | H81: D04 | AM81: - | AR81: 46.8
B82: 9QCAE | C82: Event Title | D82: Travel Dates | F82: Location | G82: Targeted Audience | H82: Trip Type
B83: Elizabeth Belenis | C83: FAS R9 Leadership Meeting | D83: 44872 | E83: 44875 | F83: San Diego, CA | G83: Leadership | H83: D03 | I83: 1091.87 | N83: 1074.75 | AW83: 9QCAE | BB83: =SUM(N83:R102) -> 4294.84 | BG83: 1ST QTR
B84: Maria Rodriguez | C84: Fort Irwin & MCLB Customer Visits | D84: 44880 | E84: 44882 | F84: Barstow, CA | G84: Customer | H84: D02 | I84: 507.14 | N84: 462.82 | BB84: =SUM(X83:AB102) -> 1401.89 | BG84: 2ND QTR
B85: Maria Rodriguez | C85: Customer Visits & Training Herlong NV | D85: 44886 | E85: 44887 | F85: Reno, NV | G85: Customer | H85: D02 | I85: 1172.4 | N85: 1091.86 | BB85: =SUM(AH83:AL102) -> 2768.36 | BG85: 3RD QTR
B86: Mark Reiss | C86: Local Travel Toll/Customer Visits | D86: 44853 | E86: 44867 | F86: Various | G86: Customer | H86: D04 | I86: - | N86: 31.8 | BB86: =SUM(AR83:AV102) -> 2856.05 | BG86: 4TH QTR
B87: Florence Francis | C87: CANCELED: Customer Visits | D87: 44880 | E87: 44882 | F87: Barstow, CA | G87: Customer | H87: D02 | I87: 738.95 | N87: -
B88: Michelle Stansberry | C88: Customer Visit | D88: 44886 | E88: 44887 | F88: Las Vegas, NV | G88: Customer | H88: D02 | I88: 268.62 | N88: 235.62
B89: Michelle Stansberry | C89: Customer Visit | D89: 44886 | E89: 44895 | F89: Las Vegas, NV | G89: Customer | H89: D02 | I89: 1016.37 | N89: 1114.43
B90: Mark Reiss | C90: CAPPO Conference | D90: 44936 | E90: 44937 | F90: Monterey, CA | G90: Conference | H90: D05 | I90: 361.5 | N90: 283.56
B91: Elizabeth Belenis | C91: VA & Executive Level Visits | D91: 44956 | E91: 44959 | F91: Santa Clara, CA | G91: Leadership | H91: D02 | S91: 1179.74 | X91: 1401.89
B92: Elizabeth Belenis | C92: CANCELLED: R9 CASE Leadership Meet | D92: 45005 | E92: 45009 | F92: San Francisco, CA | G92: Leadership | H92: D03 | S92: 2115.62 | X92: -
B93: Florence Francis | C93: RES 2023 Conference | D93: 45018 | E93: 45022 | F93: Las Vegas, NV | G93: Customers | H93: D05 | AC93: 1494.17 | AH93: 1199.32
B94: Elizabeth Belenis | C94: CANCELLED: CASE Off Site Business Meet | D94: 45033 | E94: 45035 | F94: Annapolis, MD | G94: Leadership | H94: D03 | AC94: 738.78 | AH94: -
B95: Mark Reiss | C95: Research Symposium | D95: 45055 | E95: 45057 | F95: Seaside, CA | G95: Customer | H95: D02 | AC95: 540.12 | AH95: 540.76
B96: Florence Francis | C96: Economic Summit 2023 | D96: 45097 | E96: 45100 | F96: Flagstaff, AZ | G96: Conference | H96: D05 | AC96: 745.46 | AH96: 514.14
B97: Maria Rodriguez | C97: Economic Summit 2023 | D97: 45096 | E97: 45099 | F97: Flagstaff, AZ | G97: Conference | H97: D05 | AC97: 745.46 | AH97: 514.14
B98: Maria Rodriguez | C98: CSD territory Customer Visit | D98: 45146 | E98: 45148 | F98: Barstow, CA | G98: Customer | H98: D02 | AM98: 436.12 | AR98: 422.62
B99: Mark Reiss | C99: Customer Visits DHRA/OPA and NPS | D99: 45161 | E99: 45162 | F99: Monterey, CA | G99: Customer | H99: D02 | AM99: 349.12 | AR99: 325.99
B100: Elizabeth Belenis | C100: R9 CASE Leadership Meeting | D100: 45187 | E100: 45191 | F100: Honolulu, HI | G100: Leadership | H100: D03 | AM100: 2394.67 | AR100: 2043.84
B101: Mark Reiss | C101: GOV Fastrak Deposit | D101: 45113 | E101: 45138 | F101: Various | G101: Customer | H101: D04 | AM101: - | AR101: 31.8
B102: Mark Reiss | C102: GOV Fastrak Deposit | D102: 45141 | E102: 45155 | F102: Various | G102: Customer | H102: D04 | AM102: - | AR102: 31.8
...

Sheet AAS
B2: FY23 AAS Travel
I4: 1ST QUARTER | S4: 2ND QTR | AC4: 3RD QTR | AM4: 4TH QTR | AW4: FY22 TOTAL
I5: ESTIMATE | N5: ACTUALS | S5: ESTIMATE | X5: ACTUALS | AC5: ESTIMATE | AH5: ACTUALS | AM5: ESTIMATE | AR5: ACTUALS | AW5: PLANNED | BB5: ACTUALS | BG5: BALANCE
B6: 9QFA | C6: Event Title | D6: Travel Dates | F6: Location | G6: Targeted Audience | H6: Trip Type | AW6: 350000 | BB6: =sum(BB7:BF65) -> 73541.28 | BG6: =AW6-BB6 -> 276458.72
B7: Joel Fada | C7: AAS Directors Meeting | D7: 44851 | E7: 44855 | F7: Denver, CO | G7: Leadership | H7: D03 | I7: 1734.37 | N7: 1782.83 | AW7: 9QFA | BB7: =SUM(N7:R22) -> 3250.3 | BG7: 1ST QTR
B8: Joel Fada | C8: FAS R9 Leadership Offsite Meeting | D8: 44872 | E8: 44875 | F8: San Diego, CA | G8: Leadership | H8: D03 | I8: 1532.45 | N8: 1467.47 | BB8: =SUM(X7:AB22) -> 0 | BG8: 2ND QTR
B9: Joel Fada | C9: Leadership Meeting Mileage & Parking | D9: 45048 | E9: 45049 | F9: Phoenix, AZ | G9: Leadership | H9: D04 | AC9: - | AH9: 114.68 | BB9: =SUM(AH7:AL22) -> 4650.04 | BG9: 3RD QTR
B10: Connie Mudd | C10: Leadership Meeting Mileage & Parking | D10: 45049 | E10: 45050 | F10: Phoenix, AZ | G10: Leadership | H10: D04 | AC10: - | AH10: 51.62 | BB10: =SUM(AR7:AV22) -> 10512.81 | BG10: 4TH QTR
B11: Joel Fada | C11: Government Pricing Summit Conference | D11: 45096 | E11: 45100 | F11: San Diego, CA | G11: Conference | H11: D02 | AC11: 1643.92 | AH11: 1614.12
B12: Casey Kelley | C12: F4 AAS Travel | D12: 45084 | E12: 45089 | F12: Washington, DC | G12: Leadership | H12: D03 | AC12: 1041.25 | AH12: 1203.92
B13: Jacqueline Sullo | C13: F4 AAS Travel | D13: 45084 | E13: 45086 | F13: Washington, DC | G13: Leadership | H13: D03 | AC13: 1594.97 | AH13: 1665.7
B14: Casey Kelley | C14: CANCELLED: F4 AAS Travel | D14: 45103 | E14: 45107 | F14: Washington, DC | G14: Leadership | H14: D03 | AC14: 1821.75 | AH14: -
B15: Jacqueline Sullo | C15: AAO/AAS Leadership Meet | D15: 45124 | E15: 45127 | F15: San Diego, CA | G15: Leadership | H15: D03 | AM15: 1110.47 | AR15: 1123.75
B16: Joel Fada | C16: AAO/AAS Leadership Meet | D16: 45124 | E16: 45127 | F16: San Diego, CA | G16: Leadership | H16: D03 | AM16: 1271.22 | AR16: 1252.28
B17: Jacqueline Sullo | C17: F4 AAS Travel | D17: 45131 | E17: 45135 | F17: Washington, DC | G17: Leadership | H17: D03 | AM17: 1850.62 | AR17: 2157.8
B18: Casey Kelley | C18: F4 AAS Travel | D18: 45131 | E18: 45135 | F18: Washington, DC | G18: Leadership | H18: D03 | AM18: 1886.27 | AR18: 2461.88
B19: Jacqueline Sullo | C19: F4 AAS Travel | D19: 45138 | E19: 45141 | F19: Phoenix, AZ | G19: Leadership | H19: D03 | AM19: 909.97 | AR19: 1026.17
B20: Casey Kelley | C20: AAS Core Realignment Meeting | D20: 45165 | E20: 45170 | F20: Washington, DC | G20: Leadership | H20: D03 | AM20: 2297.27 | AR20: 2391.25
B21: Joel Fada | C21: Phoenix AAS Leadership Meeting | D21: 45139 | E21: 45141 | F21: Phoenix, AZ | G21: Leadership | H21: D04 | AM21: - | AR21: 99.68
B23: 9QFAC | C23: Event Title | D23: Travel Dates | F23: Location | G23: Targeted Audience | H23: Trip Type
B24: Nathan Dolezal | C24: FAS R9 Leadership Offsite Meeting | D24: 44872 | E24: 44875 | F24: San Diego, CA | G24: Leadership | H24: D03 | I24: 1291.87 | N24: 1481.54 | AW24: 9QFAC | BB24: =SUM(N24:R37) -> 1481.54 | BG24: 1ST QTR
B25: Nathan Dolezal | C25: Alliant 2 PMR/AFCEA 2023 | D25: 44969 | E25: 44974 | F25: San Diego, CA | G25: Customer | H25: D02 | S25: 2028.32 | X25: 1707.94 | BB25: =SUM(X24:AB37) -> 2906.01 | BG25: 2ND QTR
B26: Clevester Hines | C26: AAS TDL Summit Training | D26: 44978 | E26: 44981 | F26: Jacksonville, FL | G26: Customer | H26: D02 | S26: 1137.07 | X26: 1144.59 | BB26: =SUM(AH24:AL37) -> 4253.58 | BG26: 3RD QTR
B27: Joy Wahlmann | C27: Alliant 2 PMR/AFCEA 2023 | D27: 44970 | E27: 44970 | F27: San Diego, CA | G27: Customer | H27: D04 | S27: - | X27: 53.48 | BB27: =SUM(AR24:AV37) -> 5826.73 | BG27: 4TH QTR
B28: Shontae Williams | C28: Tech Evaluation Board | D28: 45026 | E28: 45031 | F28: San Diego, CA | G28: Customer | H28: D02 | AC28: 2340.22 | AH28: 1959.12
B29: Alberto Gomez | C29: Tech Evaluation Board | D29: 45021 | E29: 45030 | F29: San Diego, CA | G29: Customer | H29: D02 | AC29: 1510.47 | AH29: 1875.08
B30: Joy Wahlmann | C30: Analytics IDIQ Eval Mileage & Parking | D30: 45027 | E30: 45030 | F30: San Diego, CA | G30: Customer | H30: D04 | AC30: - | AH30: 281.58
B31: Shontae Williams | C31: Boulder City COR Level 2 Classes Mileage | D31: 45033 | E31: 45037 | F31: Boulder City, NV | G31: Training | H31: D04 | AC31: - | AH31: 137.8
B32: Nathan Dolezal | C32: Regional AAO/AAS Leadership Meeting | D32: 45124 | E32: 45127 | F32: San Diego, CA | G32: Leadership | H32: D03 | AM32: 1423.77 | AR32: 1339.49
B33: Nathan Dolezal | C33: DHRA Client Visit | D33: 45161 | E33: 45163 | F33: Monterey, CA | G33: Customer | H33: D02 | AM33: 1230.8 | AR33: 1217.1
B34: Joy Wahlmann | C34: DHRA Client Visit | D34: 45161 | E34: 45163 | F34: Monterey, CA | G34: Customer | H34: D02 | AM34: 1193.25 | AR34: 1180.82
B35: Alberto Gomez | C35: DHRA Client Visit | D35: 45161 | E35: 45162 | F35: Monterey, CA | G35: Customer | H35: D02 | AM35: 540.3 | AR35: 559.79
B36: Brigid Cummins | C36: DHRA Client Visit | D36: 45161 | E36: 45163 | F36: Monterey, CA | G36: Customer | H36: D02 | AM36: 1536.65 | AR36: 1529.53
B38: 9QFAD | C38: Event Title | D38: Travel Dates | F38: Location | G38: Targeted Audience | H38: Trip Type
B39: Christina Bowman | C39: Conference | D39: 44846 | E39: 44848 | F39: San Jose, CA | G39: Conference | H39: D07 | I39: 880.08 | N39: 908.59 | AW39: 9QFAE | BB39: =SUM(N39:R60) -> 4688.56 | BG39: 1ST QTR
B40: Daniel Thiel | C40: BCS Technical Eval | D40: 44858 | E40: 44860 | F40: Bonita, CA | G40: Customer | H40: D02 | I40: 1053.63 | N40: 1026.56 | BB40: =SUM(X39:AB60) -> 4413.21 | BG40: 2ND QTR
B41: Diana Lynch-Maldonado | C41: BCS Technical Eval | D41: 44858 | E41: 44862 | F41: Bonita, CA | G41: Customer | H41: D02 | I41: 1396.38 | N41: 1358.46 | BB41: =SUM(AH39:AL60) -> 2547.72 | BG41: 3RD QTR
B42: Daniel Thiel | C42: FAS R9 Leadership Meet | D42: 44872 | E42: 44875 | F42: San Diego, CA | G42: Leadership | H42: D03 | I42: 1324.22 | N42: 1263.15 | BB42: =SUM(AR39:AV60) -> 10386.67 | BG42: 4TH QTR
B43: Christina Bowman | C43: Downtown SD TEB | D43: 44858 | E43: 44862 | F43: San Diego, CA | G43: Customer | H43: D04 | I43: - | N43: 131.8
B44: Pamela Ervin | C44: Customer Visit | D44: 44979 | E44: 44980 | F44: Pleasanton, CA | G44: Customer | H44: D02 | S44: 448.47 | X44: 637.73
B45: Daniel Thiel | C45: SSC IA Review Meet | D45: 44992 | E45: 44995 | F45: Los Angeles, CA | G45: Customer | H45: D02 | S45: 1274.91 | X45: 1158.19
B46: Nonya Montano | C46: SSC IA Review Meet | D46: 44992 | E46: 44995 | F46: Los Angeles, CA | G46: Customer | H46: D02 | S46: 1003.46 | X46: 1072.9
B47: Clevester Hines | C47: SSC IA Review Meet | D47: 44992 | E47: 44995 | F47: Los Angeles, CA | G47: Customer | H47: D02 | S47: 1652.46 | X47: 1466.71
B48: Christina Bowman | C48: AFCEA West 2023 Conve | D48: 44980 | E48: 44980 | F48: San Diego, CA | G48: Customer | H48: D04 | S48: - | X48: 38.84
B49: Christina Bowman | C49: Alliant 2 PMR | D49: 44970 | E49: 44970 | F49: San Diego, CA | G49: Customer | H49: D04 | S49: - | X49: 38.84
B50: Daniel Thiel | C50: FAS R9 Leadership Meet | D50: 45047 | E50: 45050 | F50: Phoenix, AZ | G50: Leadership | H50: D03 | AC50: 963.27 | AH50: 717.6
B51: Daniel Thiel | C51: Government Pricing Summit Conference | D51: 45096 | E51: 45100 | F51: San Diego, CA | G51: Customer | H51: D02 | AC51: 1838.07 | AH51: 1830.12
B52: Daniel Thiel | C52: Client Kickoff Meet | D52: 45138 | E52: 45140 | F52: Colorado Springs, CO | G52: Customer | H52: D02 | AM52: 1523.28 | AR52: 1223.29
B53: Clevester Hines | C53: Client Kickoff Meet | D53: 45138 | E53: 45141 | F53: Colorado Springs, CO | G53: Customer | H53: D02 | AM53: 1660.08 | AR53: 1741.52
B54: Michael Tabor | C54: Client Kickoff Meet | D54: 45138 | E54: 45141 | F54: Colorado Springs, CO | G54: Customer | H54: D02 | AM54: 1117.29 | AR54: 1173.04
B55: Nonya Montano | C55: NCMA World Congress 2023 | D55: 45129 | E55: 45134 | F55: Nashville, TN | G55: Conference | H55: D05 | AM55: 2100.88 | AR55: 2001.31
B56: Daniel Thiel | C56: Regional AAO/AAS Leadership Meeting | D56: 45124 | E56: 45127 | F56: San Diego, CA | G56: Meeting | H56: D03 | AM56: 1356.28 | AR56: 1282.39
B57: Clevester Hines | C57: Post Award Kickoff Meeting | D57: 45133 | E57: 45135 | F57: El Segundo, CA | G57: Customer | H57: D02 | AM57: 1010.07 | AR57: 1169.16
B58: Daniel Thiel | C58: Post Award Kickoff Meeting | D58: 45133 | E58: 45135 | F58: El Segundo, CA | G58: Customer | H58: D02 | AM58: 857.2 | AR58: 856.73
B59: Trevor Hood | C59: Post Award Kickoff Meeting | D59: 45133 | E59: 45135 | F59: El Segundo, CA | G59: Customer | H59: D02 | AM59: 939.23 | AR59: 939.23
B61: 9QFAE | C61: Event Title | D61: Travel Dates | F61: Location | G61: Targeted Audience | H61: Trip Type
B62: Karina Pohlmann | C62: SSC Leadership Meeting | D62: 44992 | E62: 44995 | F62: Los Angeles, CA | G62: Customer | H62: D02 | S62: 1296.61 | X62: 1297.53 | AW62: 9QFAE | BB62: =SUM(N62:R79) -> 0 | BG62: 1ST QTR
B63: Diana Lynch-Maldonado | C63: SSC Leadership Meeting | D63: 44992 | E63: 44995 | F63: Los Angeles, CA | G63: Customer | H63: D02 | S63: 978.78 | X63: 1035.25 | BB63: =SUM(X62:AB79) -> 2416.88 | BG63: 2ND QTR
B64: Nader Mobasseri | C64: SSC Leadership Meeting | D64: 44970 | E64: 44970 | F64: San Diego, CA | G64: Customer | H64: D04 | S64: - | X64: 84.1 | BB64: =SUM(AH62:AL79) -> 7140.63 | BG64: 3RD QTR
B65: Nader Mobasseri | C65: Front Line Leaders Conference | D65: 45030 | E65: 45039 | F65: Philadelphia, PA | G65: CANCELLED | H65: D06 | AC65: 1902.96 | AH65: - | BB65: =SUM(AR62:AV79) -> 9066.6 | BG65: 4TH QTR
B66: Karina Pohlmann | C66: FAS R9 Leadership Meeting | D66: 45047 | E66: 45050 | F66: Phoenix, AZ | G66: Leadership | H66: D03 | AC66: 1435.97 | AH66: 1472.88
B67: Karina Pohlmann | C67: Government Contract Pricing Summit | D67: 45096 | E67: 45100 | F67: San Diego, CA | G67: Conference | H67: D02 | AC67: 1539.47 | AH67: 1678.68
B68: Shannon Veen | C68: Customer Visit | D68: 45082 | E68: 45084 | F68: El Segundo, CA | G68: Customer | H68: D02 | AC68: 1416.88 | AH68: 757.88
B69: Zainab Noah | C69: SSC/FM CCA Tech Eval Team Kickoff | D69: 45081 | E69: 45088 | F69: El Segundo, CA | G69: Customer | H69: D02 | AC69: 716.48 | AH69: 716.48
B70: Alexander Chan | C70: Customer Visit | D70: 45082 | E70: 45086 | F70: El Segundo, CA | G70: Customer | H70: D02 | AC70: 1388.6 | AH70: 1307.6
B71: Tina Kennedy | C71: Customer Visit | D71: 45082 | E71: 45085 | F71: El Segundo, CA | G71: Customer | H71: D02 | AC71: 1042.36 | AH71: 1058.83
B72: Nader Mobasseri | C72: LAAFB TEBs Mileage | D72: 45082 | E72: 45086 | F72: El Segundo, CA | G72: Customer | H72: D04 | AC72: - | AH72: 148.28
B73: Zainab Noah | C73: NCMA World Congress 2023 | D73: 45129 | E73: 45134 | F73: Nashville, TN | G73: Conference | H73: D05 | AM73: 1906.82 | AR73: 2059.79
B74: Karina Pohlmann | C74: Regional AAO/AAS Leadership Meeting | D74: 45124 | E74: 45131 | F74: San Diego, CA | G74: Leadership | H74: D03 | AM74: 1033.84 | AR74: 1157.84
B75: Karina Pohlmann | C75: Internal Leadership APEX Meet | D75: 45138 | E75: 45141 | F75: Phoenix, AZ | G75: Leadership | H75: D03 | AM75: 1193.27 | AR75: 1335.85
B76: Shannon Veen | C76: Customer Visit | D76: 45146 | E76: 45148 | F76: El Segundo, CA | G76: Customer | H76: D02 | AM76: 846.88 | AR76: 776.88
B77: Michael Banks | C77: Customer Visit | D77: 45145 | E77: 45149 | F77: El Segundo, CA | G77: Customer | H77: D02 | AM77: 1443.7 | AR77: 1734.81
B78: Diana Lynch-Maldonado | C78: Customer Visit | D78: 45180 | E78: 45182 | F78: El Segundo, CA | G78: Customer | H78: D02 | AM78: 737.78 | AR78: 717.78
B79: Michael Banks | C79: Customer Visit | D79: 45179 | E79: 45182 | F79: El Segundo, CA | G79: Customer | H79: D02 | AM79: 1036.74 | AR79: 1283.65
B80: Alexander Chan | C80: Customer Visit | D80: 45180 | E80: 45182 | F80: El Segundo, CA | G80: Customer | H80: D02 | AM80: 796.6 | AR80: 893.06
B81: MISCELLANEOUS | C81: Event Title | D81: Servc/Payment Date | H81: Sub Obj Code
AW82: MISC | BB82: 0 | BG82: 1ST QTR
BB83: =X82 | BG83: 2ND QTR
BG84: 3RD QTR
BG85: 4TH QTR

Sheet PPM
B2: FY23 PPM Travel
I4: 1ST QUARTER | S4: 2ND QTR | AC4: 3RD QTR | AM4: 4TH QTR | AW4: FY 22 TOTAL
I5: ESTIMATE | N5: ACTUALS | S5: ESTIMATE | X5: ACTUALS | AC5: ESTIMATE | AH5: ACTUALS | AM5: ESTIMATE | AR5: ACTUALS | AW5: PLANNED | BB5: ACTUALS | BG5: BALANCE
B6: Q09SC000 (Sales) 9QSCB | C6: Event Title | D6: Travel Dates | F6: Location | G6: Targeted Audience | H6: Trip Type | AW6: 74300 | BB6: =sum(BB7:BF39) -> 28627.5 | BG6: =AW6-BB6 -> 45672.5
B7: Sindi Cheng-Nishimura | C7: FAS R9 Leadership Offsite Meeting | D7: 44872 | E7: 44875 | F7: San Diego, CA | G7: Leadership | H7: D03 | I7: 1076.33 | N7: 1126.06 | AW7: Q09SC000 | BB7: =SUM(N7:R39) -> 1126.06 | BG7: 1ST QTR
B8: Shirley Tarkington | C8: HAI Heli Expo 2023 | D8: 44991 | E8: 44994 | F8: Atlanta, GA | G8: Customer | H8: D02 | S8: 1391.08 | X8: 1391.08 | AW8: Sales | BB8: =SUM(X7:AB39) -> 8089.85 | BG8: 2ND QTR
B9: Sing Cheng | C9: HAI Heli Expo 2023 | D9: 44991 | E9: 44995 | F9: Atlanta, GA | G9: Customer | H9: D02 | S9: 1434.4 | X9: 1336.25 | BB9: =SUM(AH7:AL39) -> 2638.25 | BG9: 3RD QTR
B10: Zach Dean | C10: HAI Heli Expo 2023 | D10: 44991 | E10: 44993 | F10: Atlanta, GA | G10: Customer | H10: D02 | S10: 1233.95 | X10: 1264.97 | BB10: =SUM(AR7:AV39) -> 16773.34 | BG10: 4TH QTR
B11: Helen Thach | C11: Air Force Strike Board | D11: 44993 | E11: 44994 | F11: Tucson, AZ | G11: Customer | H11: D02 | S11: 1204.67 | X11: 1132.9
B12: Christian Patterson | C12: Air Force Strike Board | D12: 44993 | E12: 44994 | F12: Tucson, AZ | G12: Customer | H12: D02 | S12: 1019.75 | X12: 931.12
B13: Sindi Cheng-Nishimura | C13: Air Force Strike Board | D13: 44993 | E13: 44994 | F13: Tucson, AZ | G13: Customer | H13: D02 | S13: 802.11 | X13: 768.56
B14: Zach Dean | C14: Heli-Expo | D14: 44991 | E14: 44993 | F14: Atlanta, GA | G14: Customer | H14: D02 | S14: 1233.95 | X14: 1264.97
B15: Sindi Cheng-Nishimura | C15: FAS R9 Leadership Offsite Meeting | D15: 45047 | E15: 45050 | F15: Phoenix, AZ | G15: Leadership | H15: D03 | AC15: 1060.38 | AH15: 1144.41
B16: Zach Dean | C16: Inteagency Committee for Aviation Policy | D16: 45062 | E16: 45064 | F16: Alexandria, VA | G16: Customer | H16: D02 | AC16: 1438.38 | AH16: 1493.84
B17: Morgan Tharpe | C17: PRZ PPM Offsite | D17: 45152 | E17: 45156 | F17: Portland, OR | G17: Staff | H17: D03 | AM17: 1767.67 | AR17: 1599.97
B18: Jonathan Chan | C18: PRZ PPM Offsite | D18: 45152 | E18: 45156 | F18: Portland, OR | G18: Staff | H18: D03 | AM18: 1543.78 | AR18: 1515.43
B19: Aaron Hinde | C19: CANCELLED: PRZ PPM Offsite | D19: 45152 | E19: 45156 | F19: Portland, OR | G19: Staff | H19: D03 | AM19: 1405.78 | AR19: -
B20: Lawrence Ong | C20: PRZ PPM Offsite | D20: 45152 | E20: 45156 | F20: Portland, OR | G20: Staff | H20: D03 | AM20: 1505.78 | AR20: 1488.55
B21: Christian Patterson | C21: PRZ PPM Offsite | D21: 45152 | E21: 45156 | F21: Portland, OR | G21: Staff | H21: D03 | AM21: 1445 | AR21: 1345
B22: Debbie Leung | C22: PRZ PPM Offsite | D22: 45152 | E22: 45156 | F22: Portland, OR | G22: Staff | H22: D03 | AM22: 1487.53 | AR22: 1318.78
B23: Sing Cheng | C23: PRZ PPM Offsite | D23: 45152 | E23: 45156 | F23: Portland, OR | G23: Staff | H23: D03 | AM23: 1453.08 | AR23: 1338.08
B24: Helen Thach | C24: PRZ PPM Offsite | D24: 45152 | E24: 45156 | F24: Portland, OR | G24: Staff | H24: D03 | AM24: 1533.78 | AR24: 1460.78
B25: Shirley Tarkington | C25: PRZ PPM Offsite | D25: 45152 | E25: 45156 | F25: Portland, OR | G25: Staff | H25: D03 | AM25: 1443.21 | AR25: 1487.52
B26: Sindi Cheng-Nishimura | C26: PRZ PPM Offsite | D26: 45152 | E26: 45156 | F26: Portland, OR | G26: Staff | H26: D03 | AM26: 1502.48 | AR26: 1518.22
B27: Yik Wu | C27: PRZ PPM Offsite | D27: 45152 | E27: 45156 | F27: Portland, OR | G27: Staff | H27: D03 | AM27: 1435.77 | AR27: 1494.98
B28: Zach Dean | C28: PRZ PPM Offsite | D28: 45152 | E28: 45156 | F28: Portland, OR | G28: Staff | H28: D03 | AM28: 1480.77 | AR28: 1493.33
B29: Sindi Cheng-Nishimura | C29: CANCELLED: PPM Sales Refresher Training | D29: 45165 | E29: 45170 | F29: Fort Worth, TX | G29: Training | H29: D06 | AM29: 1785.77 | AR29: -
B30: Bonita Powell | C30: CANCELLED: PRZ PPM Offsite | D30: 45152 | E30: 45156 | F30: Portland, OR | G30: Staff | H30: D03 | AM30: 1278.56 | AR30: -
B31: Christian Patterson | C31: CANCELLED: PPM Sales Refresher Training | D31: 45165 | E31: 45170 | F31: Portland, OR | G31: Staff | H31: D03 | AM31: 1730.99 | AR31: -
B32: Helen Thach | C32: CANCELLED: PPM Sales Refresher Training | D32: 45165 | E32: 45170 | F32: Fort Worth, TX | G32: Training | H32: D06 | AM32: 1855.77 | AR32: -
B33: Sing Cheng | C33: CANCELLED: PPM Sales Refresher Training | D33: 45165 | E33: 45170 | F33: Fort Worth, TX | G33: Training | H33: D06 | AM33: 2289.22 | AR33: -
B34: Morgan Tharpe | C34: CANCELLED: PPM Sales Refresher Training | D34: 45165 | E34: 45170 | F34: Fort Worth, TX | G34: Training | H34: D06 | AM34: 2390.65 | AR34: -
B35: Shirley Tarkington | C35: NASA Palmdale Agency Visit | D35: 45187 | E35: 45188 | F35: Palmdale, CA | G35: Customer | H35: D02 | AM35: 545.37 | AR35: 577.53
B36: Christian Patterson | C36: NASA Mtg at 50 UNP | D36: 45160 | E36: 45160 | F36: San Francisco, CA | G36: Customer | H36: D04 | AM36: - | AR36: 47.86
B37: Yik Wu | C37: NASA Mtg at 50 UNP | D37: 45160 | E37: 45160 | F37: San Francisco, CA | G37: Customer | H37: D04 | AM37: - | AR37: 36.93
B38: Sing Cheng | C38: NASA Mtg at 50 UNP | D38: 45160 | E38: 45160 | F38: San Francisco, CA | G38: Customer | H38: D04 | AM38: - | AR38: 50.38
B40: K09Y1841 (U&D) 9QSCA | C40: Event Title | D40: Travel Dates | F40: Location | G40: Targeted Audience | H40: Trip Type | AW40: 99700 | BB40: =sum(BB41:BF44) -> 55265.33 | BG40: =AW40-BB40 -> 44434.67
B41: Drew Della Valle | C41: FAS R9 Leadership Offsite Meeting | D41: 44872 | E41: 44875 | F41: San Diego, CA | G41: Leadership | H41: D03 | I41: 1057.65 | N41: 1138.4 | AW41: K09Y1841 | BB41: =SUM(N41:R80) -> 2224.29 | BG41: 1ST QTR
B42: Sandra Klar | C42: FAS R9 Leadership Offsite Meeting | D42: 44872 | E42: 44875 | F42: San Diego, CA | G42: Leadership | H42: D03 | I42: 1104.87 | N42: 1085.89 | AW42: U&D | BB42: =SUM(X41:AB80) -> 15711.36 | BG42: 2ND QTR
B43: Stephon Jackson | C43: FCN 416 Conference (Presenter) | D43: 44949 | E43: 44953 | F43: San Diego, CA | G43: Customers | H43: D02 | S43: 2018.46 | X43: 1885.06 | BB43: =SUM(AH41:AL80) -> 14371.02 | BG43: 3RD QTR
B44: Joseph Adams | C44: FCN 416 Conference (Presenter) | D44: 44948 | E44: 44953 | F44: San Diego, CA | G44: Customers | H44: D02 | S44: 2206.76 | X44: 1739.47 | BB44: =SUM(AR41:AV80) -> 22958.66 | BG44: 4TH QTR
B45: Sharon Gorospe | C45: FCN416 Conference (Presenter) | D45: 44948 | E45: 44953 | F45: San Diego, CA | G45: Customers | H45: D02 | S45: 1350.47 | X45: 1150.47
B46: Sharon Gorospe | C46: SASP Review | D46: 44983 | E46: 44988 | F46: Phoenix, AZ | G46: Customers | H46: D02 | S46: 2136.22 | X46: 2397.48
B47: Stephon Jackson | C47: SASP Review | D47: 44983 | E47: 44988 | F47: Phoenix, AZ | G47: Customers | H47: D02 | S47: 1863.97 | X47: 2098.87
B48: Steven Collins | C48: SASP Review | D48: 44983 | E48: 44988 | F48: Phoenix, AZ | G48: Customers | H48: D02 | S48: 2013.96 | X48: 2174.52
B49: Stephon Jackson | C49: Air Force Strike Board Meeting | D49: 44993 | E49: 44994 | F49: Tucson, AZ | G49: Customers | H49: D02 | S49: 625.57 | X49: 645.24
B50: Sharon Gorospe | C50: Air Force Strike Board Meeting | D50: 44993 | E50: 44994 | F50: Tucson, AZ | G50: Customers | H50: D02 | S50: 783.83 | X50: 786.8
B51: Steven Collins | C51: FCN416 Conference (Presenter) | D51: 44949 | E51: 44953 | F51: San Diego, CA | G51: Customers | H51: D04 | S51: - | X51: 42
B52: Sharon Gorospe | C52: Nevada State Agency Review of Operations | D52: 45005 | E52: 45009 | F52: Reno, NV | G52: CANCELLED | H52: D02 | S52: 1128.1 | X52: -
B53: Sharon Gorospe | C53: NV Surplus Property Review of Operations | D53: 45005 | E53: 45008 | F53: Reno, NV | G53: Customers | H53: D02 | S53: 1215.05 | X53: 1356.32
B54: Stephon Jackson | C54: NV Surplus Property Review of Operations | D54: 45005 | E54: 45009 | F54: Reno, NV | G54: Customers | H54: D02 | S54: 1500.32 | X54: 1435.13
B55: Steven Collins | C55: ECS Review Training | D55: 45033 | E55: 45037 | F55: Atlanta, GA | G55: Training | H55: D02 | AC55: 1748.47 | AH55: 2008.16
B56: Stephon Jackson | C56: Alaska Review of Operations | D56: 45046 | E56: 45051 | F56: Anchorage, AK | G56: Customers | H56: D02 | AC56: 3614.74 | AH56: 2632.22
B57: Sharon Gorospe | C57: Alaska Review of Operations | D57: 45046 | E57: 45050 | F57: Anchorage, AK | G57: Customers | H57: D02 | AC57: 2557.32 | AH57: 2698.55
B58: Drew Della Valle | C58: FAS R9 Leadership Offsite Meeting | D58: 45047 | E58: 45050 | F58: Phoenix, AZ | G58: Leadership | H58: D03 | AC58: 1143.85 | AH58: 1194.45
B59: Sandra Klar | C59: FAS R9 Leadership Offsite Meeting | D59: 45047 | E59: 45050 | F59: Phoenix, AZ | G59: Leadership | H59: D03 | AC59: 1123.97 | AH59: 1194.3
B60: Sharon Gorospe | C60: ICAP | D60: 45062 | E60: 45064 | F60: Alexandria, VA | G60: Customers | H60: D02 | AC60: 1548.98 | AH60: 1561.94
B61: Randal Patterson | C61: Alaska Review of Operations | D61: 45046 | E61: 45051 | F61: Anchorage, AK | G61: Customers | H61: D02 | AC61: 2900.5 | AH61: 2896.6
B62: Steven Collins | C62: GSA Badge Pickup | D62: 45050 | E62: 45050 | F62: Los Angeles, CA | G62: Staff | H62: D02 | AC62: 184.8 | AH62: 184.8
B63: Steven Collins | C63: 2023 NASASP Conference | D63: 45125 | E63: 45127 | F63: Boise, ID | G63: Customers | H63: D02 | AM63: 1010.07 | AR63: 949.37
B64: Drew Della Valle | C64: 2023 NASASP Conference | D64: 45125 | E64: 45127 | F64: Boise, ID | G64: Customers | H64: D02 | AM64: 918.46 | AR64: 1002.11
B65: Sharon Gorospe | C65: 2023 NASASP Conference | D65: 45125 | E65: 45127 | F65: Boise, ID | G65: Customers | H65: D02 | AM65: 938.46 | AR65: 931.32
B66: Stephon Jackson | C66: 2023 NASASP Conference | D66: 45125 | E66: 45127 | F66: Boise, ID | G66: Customers | H66: D02 | AM66: 1223.77 | AR66: 1286.24
B67: Drew Della Valle | C67: PRZ PPM Offsite | D67: 45152 | E67: 45156 | F67: Portland, OR | G67: Staff | H67: D03 | AM67: 1477.8 | AR67: 1510.14
B68: Francine McCollister | C68: PRZ PPM Offsite | D68: 45152 | E68: 45156 | F68: Portland, OR | G68: Staff | H68: D03 | AM68: 1477.34 | AR68: 1398.33
B69: Sharon Gorospe | C69: PRZ PPM Offsite | D69: 45152 | E69: 45156 | F69: Portland, OR | G69: Staff | H69: D03 | AM69: 1425.78 | AR69: 1437.96
B70: Stephon Jackson | C70: PRZ PPM Offsite | D70: 45152 | E70: 45156 | F70: Portland, OR | G70: Staff | H70: D03 | AM70: 1425.78 | AR70: 1355.78
B71: Joseph Adams | C71: PRZ PPM Offsite | D71: 45152 | E71: 45156 | F71: Portland, OR | G71: Staff | H71: D03 | AM71: 1729.84
B72: Steven Collins | C72: PRZ PPM Offsite | D72: 45152 | E72: 45156 | F72: Portland, OR | G72: Staff | H72: D03 | AM72: 1767.25 | AR72: 1595.21
B73: Kevin Franken | C73: PRZ PPM Offsite | D73: 45152 | E73: 45156 | F73: Portland, OR | G73: Staff | H73: D03 | AM73: 1422.48 | AR73: 1385.26
B74: Francine McCollister | C74: BIG Conference | D74: 45165 | E74: 45170 | F74: National Harbor, MD | G74: Conference | H74: D05 | AM74: 2474.81 | AR74: 2391.7
B75: Sandra Klar | C75: PRZ PPM Offsite | D75: 45152 | E75: 45156 | F75: Portland, OR | G75: Staff | H75: D03 | AM75: 1433.78 | AR75: 1542.85
B76: Randal Patterson | C76: PRZ PPM Offsite | D76: 45152 | E76: 45156 | F76: Portland, OR | G76: Staff | H76: D03 | AM76: 1685.77 | AR76: 1481.74
B77: Sharon Gorospe | C77: State Agency Review of Operations | D77: 45159 | E77: 45162 | F77: Columbia, SC | G77: Customers | H77: D02 | AM77: 1141.88 | AR77: 1139.48
B78: Sharon Gorospe | C78: NASA Palmdale Agency Visit | D78: 45187 | E78: 45188 | F78: Palmdale, CA | G78: Customers | H78: D02 | AM78: 763.56 | AR78: 752.24
B79: Steven Collins | C79: NASA Palmdale Agency Visit | D79: 45187 | E79: 45188 | F79: Palmdale, CA | G79: Customers | H79: D02 | AM79: 654.74 | AR79: 717.24
B80: Stephon Jackson | C80: State Surplus Review of Operations | D80: 45193 | E80: 45197 | F80: Santa Fe, NM | G80: Customers | H80: D02 | AM80: 2031.38 | AR80: 2081.69
B81: MISCELLANEOUS | C81: Event Title/Desc | D81: Servc/Payment Date | H81: Sub Obj Code
AW82: MISC | BB82: =SUM(R82:V93) -> 0 | BG82: 1ST QTR
BB83: =SUM(AB82:AF93) -> 0 | BG83: 2ND QTR
BB84: =SUM(AL82:AP94) -> 0 | BG84: 3RD QTR
BB85: =SUM(AV82:AZ94) -> 0 | BG85: 4TH QTR

Sheet Pivot Table 10
A1: Trip Type | B1: 1ST QTR | C1: 2ND QTR | D1: 3RD QTR | E1: 4TH QTR | F1: TOTAL
B2: 0 | C2: 0 | D2: 0 | E2: 0
A3: B04 | B3: 156.8 | C3: 0 | D3: 0 | E3: 0 | F3: =SUM(B3:E3) -> 156.8
A4: D01 | B4: 573.15 | C4: 6590.66 | D4: 0 | E4: 0 | F4: =SUM(B4:E4) -> 7163.81
A5: D02 | B5: 8952.78 | C5: 44382.79 | D5: 33155.63 | E5: 34983.41 | F5: =SUM(B5:E5) -> 121474.61
A6: D03 | B6: 22456.46 | C6: 18542.08 | D6: 28827.33 | E6: 70375.9 | F6: =SUM(B6:E6) -> 140201.77
A7: D04 | B7: 504.13 | C7: 309.64 | D7: 1195.49 | E7: 908.56 | F7: =SUM(B7:E7) -> 2917.82
A8: D05 | B8: 0 | C8: 3216.77 | D8: 8631.49 | E8: 8388.88 | F8: =SUM(B8:E8) -> 20237.14
A9: D06 | B9: 0 | C9: 0 | D9: 0 | E9: 0 | F9: =SUM(B9:E9) -> 0
A10: D07 | B10: 908.59 | C10: 0 | D10: 0 | E10: 0 | F10: =SUM(B10:E10) -> 908.59
A11: D40 | B11: 0 | C11: 6152.77 | D11: 13264.93 | E11: 15387.37
A12: F4G | B12: 555.93 | C12: 474.57 | D12: 999.81 | E12: 271.88
A13: L01 | B13: 0 | C13: 14.33 | D13: 0 | E13: 0
A14: Sub Obj Code | B14: 0 | C14: 0 | D14: 0 | E14: 0
A15: Trip Type | B15: 0 | C15: 0 | D15: 0 | E15: 0

Sheet RCPivot Table
F1: TOTAL
F2: =SUM(B2:E2) -> 5822.28 | G2: Mission/Oper
F3: =SUM(B3:E3) -> 30296.04 | G3: Internal GSA Meeting
F4: =SUM(B4:E4) -> 679.92

Sheet CASEPivot Tables
A1: Trip Type | B1: 1st qtr | C1: 2nd qtr | D1: 3rd qtr | E1: 4th qtr | F1: TOTAL
A2: D01 | B2: 0 | C2: 6590.66 | D2: 0 | E2: 0 | F2: =SUM(B2:E2) -> 6590.66
A3: D02 | B3: 7193.69 | C3: 9789.91 | D3: 8189.21 | E3: 8549.8 | F3: =SUM(B3:E3) -> 33722.61
A4: D03 | B4: 10977.29 | C4: 11960.11 | D4: 10789.19 | E4: 15782.33 | F4: =SUM(B4:E4) -> 49508.92
A5: D04 | B5: 372.33 | C5: 52.38 | D5: 0 | E5: 536.48 | F5: =SUM(B5:E5) -> 961.19
A6: D05 | B6: 283.56 | C6: 3216.77 | D6: 8631.49 | E6: 1936.08 | F6: =SUM(B6:E6) -> 14067.9
F7: =SUM(B7:E7) -> 0
F8: =SUM(B8:E8) -> 0

Sheet AAS Pivot Table
A1: Trip Type | B1: 1st qtr | C1: 2nd qtr | D1: 3rd qtr | E1: 4th qtr | F1: TOTAL
B2: 0 | C2: 0 | D2: 0 | E2: 0 | F2: =SUM(B2:E2) -> 0
A3: D02 | B3: 2385.02 | C3: 9520.84 | D3: 7278.44 | E3: 11590.21 | F3: =SUM(B3:E3) -> 30774.51
A4: D03 | B4: 5994.99 | C4: 0 | D4: 3587.22 | E4: 13035.01 | F4: =SUM(B4:E4) -> 22617.22
F5: =SUM(B5:E5) -> 0

Sheet PPMSales Pivot Tables
A1: Trip Type | B1: 1st qtr | C1: 2nd qtr | D1: 3rd qtr | E1: 4th qtr | F1: TOTAL
A2: D02 | B2: 0 | C2: 8089.85 | D2: 1493.84 | E2: 577.53 | F2: =SUM(B2:E2) -> 10161.22
A3: D06 | B3: 0 | C3: 0 | D3: 0 | E3: 0 | F3: =SUM(B3:E3) -> 0
A4: Grand Total | B4: 0 | C4: 8089.85 | D4: 1493.84 | E4: 577.53 | F4: =SUM(B4:E4) -> 10161.22
F5: =SUM(B5:E5) -> 0
F6: =SUM(B6:E6) -> 0
F7: =SUM(B7:E7) -> 0
F8: =SUM(B8:E8) -> 0

Sheet PPMU&D Pivot Tables
A1: Trip Type | B1: 1st qtr | C1: 2nd qtr | D1: 3rd qtr | E1: 4th qtr | F1: TOTAL
A2: D02 | B2: 0 | C2: 15669.36 | D2: 11982.27 | E2: 8859.69 | F2: =SUM(B2:E2) -> 36511.32
A3: D05 | B3: 0 | C3: 0 | D3: 0 | E3: 2391.7 | F3: =SUM(B3:E3) -> 2391.7
A4: Grand Total | B4: 0 | C4: 15669.36 | D4: 11982.27 | E4: 11251.39 | F4: =SUM(B4:E4) -> 38903.02
F5: =SUM(B5:E5) -> 0
